.gitignore
CONTRIBUTORS.txt
README.txt
TODO.txt
base.cfg
bootstrap.py
buildout.cfg
plone3.2.cfg
plone3.3.cfg
plone4.cfg
setup.py
docs/HISTORY.txt
docs/INSTALL.txt
docs/LICENSE.GPL
docs/LICENSE.txt
src/borg/__init__.py
src/borg.project.egg-info/PKG-INFO
src/borg.project.egg-info/SOURCES.txt
src/borg.project.egg-info/dependency_links.txt
src/borg.project.egg-info/entry_points.txt
src/borg.project.egg-info/namespace_packages.txt
src/borg.project.egg-info/not-zip-safe
src/borg.project.egg-info/requires.txt
src/borg.project.egg-info/top_level.txt
src/borg/project/README.txt
src/borg/project/TODO.txt
src/borg/project/__init__.py
src/borg/project/config.py
src/borg/project/configure.zcml
src/borg/project/content.py
src/borg/project/handlers.py
src/borg/project/interfaces.py
src/borg/project/localroles.py
src/borg/project/setuphandlers.py
src/borg/project/utils.py
src/borg/project/version.txt
src/borg/project/vocabularies.py
src/borg/project/Extensions/Install.py
src/borg/project/browser/__init__.py
src/borg/project/browser/configure.zcml
src/borg/project/browser/project.png
src/borg/project/browser/project.pt
src/borg/project/browser/project.py
src/borg/project/locales/borg.project.pot
src/borg/project/locales/de/LC_MESSAGES/borg.project.po
src/borg/project/locales/de/LC_MESSAGES/plone.po
src/borg/project/profiles/plone3/metadata.xml
src/borg/project/profiles/plone4/metadata.xml
src/borg/project/profiles/plone4/types.xml
src/borg/project/profiles/plone4/types/b-org_Project.xml
src/borg/project/profiles/zbase/import_steps.xml
src/borg/project/profiles/zbase/metadata.xml
src/borg/project/profiles/zbase/types.xml
src/borg/project/profiles/zbase/workflows.xml
src/borg/project/profiles/zbase/types/b-org_Project.xml
src/borg/project/profiles/zbase/workflows/borg_project_content_workflow/definition.xml
src/borg/project/profiles/zbase/workflows/borg_project_workflow/definition.xml
src/borg/project/tests/__init__.py
src/borg/project/tests/base.py
src/borg/project/tests/test_browser.py
src/borg/project/tests/test_doctests.py