Metadata-Version: 1.0
Name: borg.project
Version: 1.1rc9
Summary: Ability to create project workspaces with local workflow
Home-page: http://svn.plone.org/svn/collective/borg/borg.project
Author: Martin Aspeli
Author-email: optilude@gmx.net
License: GPL
Keywords: Plone project workspace teamspace
Platform: UNKNOWN
Classifier: Framework :: Zope2
Classifier: Framework :: Zope3
Classifier: Programming Language :: Python
Classifier: Topic :: Software Development :: Libraries :: Python Modules
